omg_ses_kutuphanesi/__init__.py
omg_ses_kutuphanesi/omg-duz.wav
omg_ses_kutuphanesi/omg-yankılı.wav
omg_ses_kutuphanesi/ses.wav
omg_ses_kutuphanesi/sesler.py
omg_ses_kutuphanesi-1.1.0.dist-info/METADATA
omg_ses_kutuphanesi-1.1.0.dist-info/WHEEL
omg_ses_kutuphanesi-1.1.0.dist-info/top_level.txt
omg_ses_kutuphanesi-1.1.0.dist-info/RECORD
