Metadata-Version: 2.4
Name: omg_ses_kutuphanesi
Version: 1.1.0
Summary: Basit ses çalma kütüphanesi
Home-page: https://github.com/kullanici/omg_ses_kutuphanesi
Author: Recep
Author-email: seninmailin@gmail.com
Classifier: Programming Language :: Python :: 3
Classifier: License :: OSI Approved :: MIT License
Requires-Python: >=3.6
Requires-Dist: pygame>=2.0.0
Dynamic: author
Dynamic: author-email
Dynamic: classifier
Dynamic: home-page
Dynamic: requires-dist
Dynamic: requires-python
Dynamic: summary
